cartola/__init__.py
cartola/config.py
cartola/dt.py
cartola/exception.py
cartola/fs.py
cartola/ftext.py
cartola/net.py
cartola/pagination.py
cartola/security.py
cartola/sysexits.py
cartola/xray.py
cartola-0.21.dist-info/licenses/LICENSE
cartola-0.21.dist-info/METADATA
cartola-0.21.dist-info/WHEEL
cartola-0.21.dist-info/top_level.txt
cartola-0.21.dist-info/RECORD
