Metadata-Version: 2.4
Name: cartola
Version: 0.21
Summary: Candango's Shared Functions.
Author-email: Flavio Garcia <piraz@candango.org>
License-Expression: Apache-2.0
Project-URL: Homepage, https://github.com/candango/cartola
Classifier: Development Status :: 5 - Production/Stable
Classifier: Environment :: Console
Classifier: Environment :: Web Environment
Classifier: Intended Audience :: Developers
Classifier: Intended Audience :: System Administrators
Classifier: Programming Language :: Python :: 3
Classifier: Programming Language :: Python :: 3.9
Classifier: Programming Language :: Python :: 3.10
Classifier: Programming Language :: Python :: 3.11
Classifier: Programming Language :: Python :: 3.12
Classifier: Programming Language :: Python :: 3 :: Only
Classifier: Topic :: Software Development :: Libraries
Requires-Python: >=3.9
License-File: LICENSE
Requires-Dist: pyyaml==6.0.3
Dynamic: license-file
